print_at_soc/__init__.py
print_at_soc/__main__.py
print_at_soc/_post_install.py
print_at_soc/cli.py
print_at_soc/config.py
print_at_soc/downloader.py
print_at_soc-0.1.0.data/data/print_at_soc.pth
print_at_soc-0.1.0.dist-info/licenses/LICENSE
print_at_soc-0.1.0.dist-info/METADATA
print_at_soc-0.1.0.dist-info/WHEEL
print_at_soc-0.1.0.dist-info/entry_points.txt
print_at_soc-0.1.0.dist-info/top_level.txt
print_at_soc-0.1.0.dist-info/RECORD
