Metadata-Version: 2.4
Name: print-at-soc
Version: 0.1.0
Summary: Print@SoC - Smart Printing for NUS SoC - Python CLI wrapper for desktop application
Author-email: Silan Hu <silan.hu@u.nus.edu>
License: MIT
Project-URL: Homepage, https://github.com/Qingbolan/Print-SoC
Project-URL: Repository, https://github.com/Qingbolan/Print-SoC
Project-URL: Issues, https://github.com/Qingbolan/Print-SoC/issues
Keywords: nus,soc,printing,ssh,pdf,desktop-application
Classifier: Development Status :: 3 - Alpha
Classifier: Intended Audience :: Education
Classifier: Topic :: Printing
Classifier: Topic :: Utilities
Classifier: License :: OSI Approved :: MIT License
Classifier: Programming Language :: Python :: 3
Classifier: Programming Language :: Python :: 3.8
Classifier: Programming Language :: Python :: 3.9
Classifier: Programming Language :: Python :: 3.10
Classifier: Programming Language :: Python :: 3.11
Classifier: Programming Language :: Python :: 3.12
Classifier: Operating System :: OS Independent
Requires-Python: >=3.8
License-File: LICENSE
Dynamic: license-file
